nb_conda_store_kernels
