Metadata-Version: 2.1
Name: nb-conda-store-kernels
Version: 0.1.4
Summary: Launch Jupyter kernels from Conda-Store
Home-page: https://github.com/Quansight/nb_conda_store_kernels
Author: Christopher Ostrouchov
Author-email: chris.ostrouchov@gmail.com
License: BSD License
Project-URL: Bug Reports, https://github.com/quansight/nb_conda_store_kernels
Project-URL: Documentation, https://nb_conda_store_kernels.readthedocs.io/
Project-URL: Source, https://github.com/quansight/nb_conda_store_kernels
Keywords: conda
Classifier: Development Status :: 3 - Alpha
Classifier: Intended Audience :: Developers
Classifier: Topic :: Software Development :: Build Tools
Classifier: License :: OSI Approved :: BSD License
Classifier: Programming Language :: Python :: 3
Classifier: Programming Language :: Python :: 3.7
Classifier: Programming Language :: Python :: 3.8
Classifier: Programming Language :: Python :: 3.9
Classifier: Programming Language :: Python :: 3 :: Only
Provides-Extra: dev
License-File: LICENSE
